AIEmailAutomationUtility/EmailReplyAssistant.py
AIEmailAutomationUtility/Email_Classification.py
AIEmailAutomationUtility/Email_DocumentUploader.py
AIEmailAutomationUtility/Email_Draft.py
AIEmailAutomationUtility/Email_Read.py
AIEmailAutomationUtility/Email_Upload_Document.py
AIEmailAutomationUtility/Process_Category.py
AIEmailAutomationUtility/Save_Draft.py
AIEmailAutomationUtility/Save_Transaction.py
AIEmailAutomationUtility/__init__.py
aiemailautomationutility-0.0.49.dist-info/LICENCE.txt
aiemailautomationutility-0.0.49.dist-info/METADATA
aiemailautomationutility-0.0.49.dist-info/WHEEL
aiemailautomationutility-0.0.49.dist-info/top_level.txt
aiemailautomationutility-0.0.49.dist-info/RECORD
