Metadata-Version: 2.1
Name: aiemailautomationutility
Version: 0.0.49
Summary: Update the priority order to ensure that E-Merck appears before Merck in the priority list.
Author: Proteus Technology PVT. LTD.
Author-email: <apps@baseinformation.com>
Keywords: python,first package
Classifier: Development Status :: 3 - Alpha
Classifier: Intended Audience :: Education
Classifier: Programming Language :: Python :: 2
Classifier: Programming Language :: Python :: 3
Classifier: Operating System :: MacOS :: MacOS X
Classifier: Operating System :: Microsoft :: Windows
License-File: LICENCE.txt
